clockify/__init__.py
clockify/abstract_clockify.py
clockify/client.py
clockify/factories.py
clockify/membership.py
clockify/project.py
clockify/task.py
clockify/timeentry.py
clockify/user.py
clockify/workspace.py
clockifya-0.0.2.dist-info/METADATA
clockifya-0.0.2.dist-info/WHEEL
clockifya-0.0.2.dist-info/top_level.txt
clockifya-0.0.2.dist-info/RECORD
