Metadata-Version: 2.1
Name: clockifya
Version: 0.0.2
Summary: Clockify is the only truly free time tracker and timesheet app for teams of all sizes. Unlike all the other time trackers, Clockify is available for an unlimited numbers of users for free
Home-page: https://gitlab.com/integration_seon/libs/application/clockify
Author: Paulo Sergio dos Santos Junior
Author-email: paulossjunior@gmail.com
License: UNKNOWN
Platform: UNKNOWN
Classifier: Programming Language :: Python :: 3
Classifier: License :: OSI Approved :: MIT License
Classifier: Operating System :: OS Independent
Requires-Dist: factory-boy
Requires-Dist: requests
